capnpy/__init__.pxd
capnpy/__init__.py
capnpy/__main__.py
capnpy/_hash.c
capnpy/_hash.h
capnpy/_hash.pxd
capnpy/_hash.py
capnpy/_hash.pyx
capnpy/_hash_cpython.c
capnpy/_util.c
capnpy/_util.h
capnpy/_util.pyx
capnpy/annotate.capnp
capnpy/annotate.py
capnpy/annotate_extended.py
capnpy/anypointer.py
capnpy/blob.c
capnpy/blob.pxd
capnpy/blob.py
capnpy/buffered.c
capnpy/buffered.pxd
capnpy/buffered.py
capnpy/convert_case.py
capnpy/enum.c
capnpy/enum.pxd
capnpy/enum.py
capnpy/filelike.c
capnpy/filelike.pxd
capnpy/filelike.py
capnpy/list.c
capnpy/list.pxd
capnpy/list.py
capnpy/message.c
capnpy/message.pxd
capnpy/message.py
capnpy/packing.c
capnpy/packing.pxd
capnpy/packing.py
capnpy/packing.pyx
capnpy/printer.py
capnpy/ptr.c
capnpy/ptr.h
capnpy/ptr.pxd
capnpy/ptr.py
capnpy/ptr.pyx
capnpy/reflection.py
capnpy/schema.capnp
capnpy/schema.py
capnpy/schema_extended.py
capnpy/struct_.c
capnpy/struct_.pxd
capnpy/struct_.py
capnpy/type.c
capnpy/type.pxd
capnpy/type.py
capnpy/util.py
capnpy/benchmarks/__init__.py
capnpy/benchmarks/benchmarks.capnp
capnpy/benchmarks/benchmarks_base.capnp
capnpy/benchmarks/bigtree.dump
capnpy/benchmarks/support.py
capnpy/benchmarks/test_benchmarks.py
capnpy/benchmarks/test_buffered.py
capnpy/benchmarks/test_ctor.py
capnpy/benchmarks/test_message.py
capnpy/benchmarks/test_unpack.py
capnpy/compiler/__init__.py
capnpy/compiler/compiler.py
capnpy/compiler/distutils.py
capnpy/compiler/enum.py
capnpy/compiler/field.py
capnpy/compiler/fieldtree.py
capnpy/compiler/misc.py
capnpy/compiler/module.py
capnpy/compiler/node.py
capnpy/compiler/request.py
capnpy/compiler/struct_.py
capnpy/compiler/structor.py
capnpy/compiler/util.py
capnpy/ext/__init__.py
capnpy/floatrepr/__init__.py
capnpy/floatrepr/build.py
capnpy/floatrepr/kjwrap.cc
capnpy/segment/__init__.py
capnpy/segment/_copy_list.py
capnpy/segment/_copy_pointer.h
capnpy/segment/_copy_pointer.py
capnpy/segment/_copy_pointer.pyx
capnpy/segment/base.c
capnpy/segment/base.pxd
capnpy/segment/base.py
capnpy_agates-0.9.2rc1.dist-info/LICENSE
capnpy_agates-0.9.2rc1.dist-info/METADATA
capnpy_agates-0.9.2rc1.dist-info/WHEEL
capnpy_agates-0.9.2rc1.dist-info/entry_points.txt
capnpy_agates-0.9.2rc1.dist-info/top_level.txt
capnpy_agates-0.9.2rc1.dist-info/RECORD
